README.rst
setup.cfg
setup.py
datetime_diff/__init__.py
datetime_diff.egg-info/PKG-INFO
datetime_diff.egg-info/SOURCES.txt
datetime_diff.egg-info/dependency_links.txt
datetime_diff.egg-info/top_level.txt