Metadata-Version: 1.1
Name: datetime-diff
Version: 0.0.1
Summary: Extension to the datetime module
Home-page: https://github.com/AraHaan/datetime_diff
Author: Decorater
Author-email: seandhunt_7@yahoo.com
License: MIT
Download-URL: https://github.com/AraHaan/datetime_diff
Platform: Any
Classifier: Development Status :: 4 - Beta
Classifier: Intended Audience :: Developers
Classifier: License :: OSI Approved :: MIT License
Classifier: Natural Language :: English
Classifier: Operating System :: OS Independent
Classifier: Programming Language :: Python :: 2
Classifier: Programming Language :: Python :: 3
Classifier: Topic :: Software Development :: Libraries
Classifier: Topic :: Software Development :: Libraries :: Python Modules
Classifier: Topic :: Utilities
